{
  "users": [
    {
      "contactNumber": "9100000001",
      "salaryPerMonth": "25000",
      "roleId": "salesman",
      "roles": ["salesman"],
      "name": "Rahul Sharma",
      "email": "rahul.sharma@example.com",
      "isActive": true,
      "password": "Rahul@123",
      "city": "Indore",
      "state": "Madhya Pradesh",
      "pincode": "452001",
      "country": "India"
    },
    {
      "contactNumber": "9100000002",
      "salaryPerMonth": "24500",
      "roleId": "salesman",
      "roles": ["salesman"],
      "name": "Vikas Patel",
      "email": "vikas.patel@example.com",
      "isActive": true,
      "password": "Vikas@123",
      "city": "Bhopal",
      "state": "Madhya Pradesh",
      "pincode": "462001",
      "country": "India"
    },
    {
      "contactNumber": "9100000003",
      "salaryPerMonth": "26000",
      "roleId": "salesman",
      "roles": ["salesman"],
      "name": "Sanjay Kumar",
      "email": "sanjay.kumar@example.com",
      "isActive": true,
      "password": "Sanjay@123",
      "city": "Jaipur",
      "state": "Rajasthan",
      "pincode": "302001",
      "country": "India"
    },
    {
      "contactNumber": "9100000004",
      "salaryPerMonth": "25500",
      "roleId": "salesman",
      "roles": ["salesman"],
      "name": "Deepak Yadav",
      "email": "deepak.yadav@example.com",
      "isActive": true,
      "password": "Deepak@123",
      "city": "Surat",
      "state": "Gujarat",
      "pincode": "395003",
      "country": "India"
    },
    {
      "contactNumber": "9100000005",
      "salaryPerMonth": "24800",
      "roleId": "salesman",
      "roles": ["salesman"],
      "name": "Mohit Jain",
      "email": "mohit.jain@example.com",
      "isActive": true,
      "password": "Mohit@123",
      "city": "Nagpur",
      "state": "Maharashtra",
      "pincode": "440001",
      "country": "India"
    },
    {
      "contactNumber": "9100000006",
      "salaryPerMonth": "20000",
      "roleId": "telecaller",
      "roles": ["telecaller"],
      "name": "Anita Verma",
      "email": "anita.verma@example.com",
      "isActive": true,
      "password": "Anita@123",
      "city": "Ahmedabad",
      "state": "Gujarat",
      "pincode": "380001",
      "country": "India"
    },
    {
      "contactNumber": "9100000007",
      "salaryPerMonth": "19500",
      "roleId": "telecaller",
      "roles": ["telecaller"],
      "name": "Pooja Singh",
      "email": "pooja.singh@example.com",
      "isActive": true,
      "password": "Pooja@123",
      "city": "Mumbai",
      "state": "Maharashtra",
      "pincode": "400001",
      "country": "India"
    },
    {
      "contactNumber": "9100000008",
      "salaryPerMonth": "20500",
      "roleId": "telecaller",
      "roles": ["telecaller"],
      "name": "Kiran Desai",
      "email": "kiran.desai@example.com",
      "isActive": true,
      "password": "Kiran@123",
      "city": "Pune",
      "state": "Maharashtra",
      "pincode": "411001",
      "country": "India"
    },
    {
      "contactNumber": "9100000009",
      "salaryPerMonth": "21000",
      "roleId": "telecaller",
      "roles": ["telecaller"],
      "name": "Megha Rao",
      "email": "megha.rao@example.com",
      "isActive": true,
      "password": "Megha@123",
      "city": "Lucknow",
      "state": "Uttar Pradesh",
      "pincode": "226001",
      "country": "India"
    },
    {
      "contactNumber": "9100000010",
      "salaryPerMonth": "19800",
      "roleId": "telecaller",
      "roles": ["telecaller"],
      "name": "Priya Nair",
      "email": "priya.nair@example.com",
      "isActive": true,
      "password": "Priya@123",
      "city": "Kochi",
      "state": "Kerala",
      "pincode": "682001",
      "country": "India"
    },
    {
      "contactNumber": "9100000011",
      "salaryPerMonth": "40000",
      "roleId": "manager",
      "roles": ["manager"],
      "name": "Alok Mishra",
      "email": "alok.mishra@example.com",
      "isActive": true,
      "password": "Alok@123",
      "city": "Kanpur",
      "state": "Uttar Pradesh",
      "pincode": "208001",
      "country": "India"
    },
    {
      "contactNumber": "9100000012",
      "salaryPerMonth": "41500",
      "roleId": "manager",
      "roles": ["manager"],
      "name": "Bhavesh Shah",
      "email": "bhavesh.shah@example.com",
      "isActive": true,
      "password": "Bhavesh@123",
      "city": "Vadodara",
      "state": "Gujarat",
      "pincode": "390001",
      "country": "India"
    },
    {
      "contactNumber": "9100000013",
      "salaryPerMonth": "41000",
      "roleId": "manager",
      "roles": ["manager"],
      "name": "Chandan Roy",
      "email": "chandan.roy@example.com",
      "isActive": true,
      "password": "Chandan@123",
      "city": "Kolkata",
      "state": "West Bengal",
      "pincode": "700001",
      "country": "India"
    },
    {
      "contactNumber": "9100000014",
      "salaryPerMonth": "40500",
      "roleId": "manager",
      "roles": ["manager"],
      "name": "Dinesh Reddy",
      "email": "dinesh.reddy@example.com",
      "isActive": true,
      "password": "Dinesh@123",
      "city": "Chennai",
      "state": "Tamil Nadu",
      "pincode": "600001",
      "country": "India"
    },
    {
      "contactNumber": "9100000015",
      "salaryPerMonth": "42000",
      "roleId": "manager",
      "roles": ["manager"],
      "name": "Farhan Khan",
      "email": "farhan.khan@example.com",
      "isActive": true,
      "password": "Farhan@123",
      "city": "Raipur",
      "state": "Chhattisgarh",
      "pincode": "492001",
      "country": "India"
    },
    {
      "contactNumber": "9100000016",
      "salaryPerMonth": "28000",
      "roleId": "teleadmin",
      "roles": ["teleadmin"],
      "name": "Ritika Jain",
      "email": "ritika.jain@example.com",
      "isActive": true,
      "password": "Ritika@123",
      "city": "Indore",
      "state": "Madhya Pradesh",
      "pincode": "452001",
      "country": "India"
    },
    {
      "contactNumber": "9100000017",
      "salaryPerMonth": "29000",
      "roleId": "teleadmin",
      "roles": ["teleadmin"],
      "name": "Sonal Mehta",
      "email": "sonal.mehta@example.com",
      "isActive": true,
      "password": "Sonal@123",
      "city": "Ahmedabad",
      "state": "Gujarat",
      "pincode": "380001",
      "country": "India"
    },
    {
      "contactNumber": "9100000018",
      "salaryPerMonth": "28500",
      "roleId": "teleadmin",
      "roles": ["teleadmin"],
      "name": "Gaurav Kulkarni",
      "email": "gaurav.kulkarni@example.com",
      "isActive": true,
      "password": "Gaurav@123",
      "city": "Pune",
      "state": "Maharashtra",
      "pincode": "411001",
      "country": "India"
    },
    {
      "contactNumber": "9100000019",
      "salaryPerMonth": "29500",
      "roleId": "teleadmin",
      "roles": ["teleadmin"],
      "name": "Harpreet Kaur",
      "email": "harpreet.kaur@example.com",
      "isActive": true,
      "password": "Harpreet@123",
      "city": "Ludhiana",
      "state": "Punjab",
      "pincode": "141001",
      "country": "India"
    },
    {
      "contactNumber": "9100000020",
      "salaryPerMonth": "30000",
      "roleId": "teleadmin",
      "roles": ["teleadmin"],
      "name": "Imran Sheikh",
      "email": "imran.sheikh@example.com",
      "isActive": true,
      "password": "Imran@123",
      "city": "Hyderabad",
      "state": "Telangana",
      "pincode": "500001",
      "country": "India"
    }
  ]
}

